{
  "player_build_data": [
    {
      "type": "playerBuildTimingData",
      "msg": {
        "build_event_id": "b82958f2396ff4ff882cfc5d77007ee4",
        "build_player": 36925,
        "preprocess_player": 381,
        "produce_player_script_assemblies": 8945,
        "build_scripts_dlls": 2207,
        "writing_asset_files": 21056,
        "postprocess_built_player": 613,
        "node_summary_table": [
          {
            "name": "Csc",
            "duration": 461
          },
          {
            "name": "Csc",
            "duration": 510
          },
          {
            "name": "Csc",
            "duration": 679
          },
          {
            "name": "Csc",
            "duration": 316
          },
          {
            "name": "Csc",
            "duration": 406
          },
          {
            "name": "Csc",
            "duration": 402
          },
          {
            "name": "Csc",
            "duration": 287
          },
          {
            "name": "Csc",
            "duration": 849
          },
          {
            "name": "Csc",
            "duration": 334
          },
          {
            "name": "Csc",
            "duration": 1103
          },
          {
            "name": "Csc",
            "duration": 489
          },
          {
            "name": "Csc",
            "duration": 332
          },
          {
            "name": "Csc",
            "duration": 317
          },
          {
            "name": "Csc",
            "duration": 473
          },
          {
            "name": "Csc",
            "duration": 425
          },
          {
            "name": "Csc",
            "duration": 422
          },
          {
            "name": "Csc",
            "duration": 310
          },
          {
            "name": "Csc",
            "duration": 546
          },
          {
            "name": "Csc",
            "duration": 513
          },
          {
            "name": "Csc",
            "duration": 470
          },
          {
            "name": "Csc",
            "duration": 292
          },
          {
            "name": "Csc",
            "duration": 1457
          },
          {
            "name": "Csc",
            "duration": 562
          },
          {
            "name": "Csc",
            "duration": 390
          },
          {
            "name": "Csc",
            "duration": 439
          },
          {
            "name": "Csc",
            "duration": 376
          },
          {
            "name": "Csc",
            "duration": 342
          },
          {
            "name": "Csc",
            "duration": 381
          },
          {
            "name": "Csc",
            "duration": 639
          },
          {
            "name": "Csc",
            "duration": 359
          },
          {
            "name": "Csc",
            "duration": 260
          },
          {
            "name": "Csc",
            "duration": 450
          },
          {
            "name": "Csc",
            "duration": 641
          },
          {
            "name": "Csc",
            "duration": 510
          },
          {
            "name": "Csc",
            "duration": 261
          },
          {
            "name": "Csc",
            "duration": 244
          },
          {
            "name": "Csc",
            "duration": 729
          },
          {
            "name": "Csc",
            "duration": 250
          },
          {
            "name": "Csc",
            "duration": 579
          },
          {
            "name": "Csc",
            "duration": 357
          },
          {
            "name": "Csc",
            "duration": 230
          },
          {
            "name": "Csc",
            "duration": 426
          },
          {
            "name": "Csc",
            "duration": 416
          }
        ]
      },
      "version": 1
    }
  ]
}